README.md
setup.py
retail/__init__.py
retailcrm_api.egg-info/PKG-INFO
retailcrm_api.egg-info/SOURCES.txt
retailcrm_api.egg-info/dependency_links.txt
retailcrm_api.egg-info/requires.txt
retailcrm_api.egg-info/top_level.txt