Metadata-Version: 1.2
Name: retailcrm-api
Version: 0.0.6
Summary: RetailCRM api v5 wrapper
Home-page: https://github.com/bzdvdn/retailcrm-api
Author: bzdvdn
Author-email: bzdv.dn@gmail.com
License: MIT
Platform: UNKNOWN
Requires-Python: >=3.6
